podlens/__init__.py
podlens/apple_podcast_ch.py
podlens/apple_podcast_en.py
podlens/auto_ch.py
podlens/auto_en.py
podlens/cli_ch.py
podlens/cli_en.py
podlens/core_ch.py
podlens/core_en.py
podlens/email_service_ch.py
podlens/email_service_en.py
podlens/notion_ch.py
podlens/notion_en.py
podlens/visual_ch.py
podlens/visual_en.py
podlens/youtube_ch.py
podlens/youtube_en.py
podlens-1.2.23.dist-info/licenses/LICENSE
podlens-1.2.23.dist-info/METADATA
podlens-1.2.23.dist-info/WHEEL
podlens-1.2.23.dist-info/entry_points.txt
podlens-1.2.23.dist-info/top_level.txt
podlens-1.2.23.dist-info/RECORD
