Metadata-Version: 2.4
Name: podlens
Version: 1.2.23
Summary: Intelligent Podcast & Youtube Transcription & Understanding AI Agent
Author-email: Dunyuan Zha <henryzha@outlook.com>
Maintainer-email: Dunyuan Zha <henryzha@outlook.com>
License: MIT
Project-URL: Homepage, https://github.com/512z/podlens/tree/main
Project-URL: Repository, https://github.com/512z/podlens/tree/main
Keywords: podcast,transcription,summary,youtube,apple podcast,whisper,ai
Classifier: Development Status :: 4 - Beta
Classifier: Intended Audience :: End Users/Desktop
Classifier: Topic :: Multimedia :: Sound/Audio
Classifier: License :: OSI Approved :: MIT License
Classifier: Programming Language :: Python :: 3
Classifier: Programming Language :: Python :: 3.8
Classifier: Programming Language :: Python :: 3.9
Classifier: Programming Language :: Python :: 3.10
Classifier: Programming Language :: Python :: 3.11
Classifier: Programming Language :: Python :: 3.12
Classifier: Operating System :: OS Independent
Requires-Python: >=3.8
License-File: LICENSE
Requires-Dist: requests
Requires-Dist: feedparser>=6.0.0
Requires-Dist: python-dotenv
Requires-Dist: google-generativeai
Requires-Dist: beautifulsoup4
Requires-Dist: tqdm
Requires-Dist: mlx-whisper
Requires-Dist: groq
Requires-Dist: openai-whisper
Requires-Dist: youtube-transcript-api
Requires-Dist: yt-dlp
Requires-Dist: schedule
Dynamic: license-file
